contextr/__init__.py
contextr/cli.py
contextr/main.py
contextr/commands/__init__.py
contextr/commands/package.py
contextr/utils/__init__.py
contextr/utils/helpers.py
repo_contextr-0.1.0.dist-info/METADATA
repo_contextr-0.1.0.dist-info/WHEEL
repo_contextr-0.1.0.dist-info/entry_points.txt
repo_contextr-0.1.0.dist-info/licenses/LICENSE
repo_contextr-0.1.0.dist-info/RECORD
