Metadata-Version: 2.4
Name: repo-contextr
Version: 0.1.0
Summary: A powerful Repository Context Packager CLI tool for LLMs
Project-URL: Homepage, https://github.com/dharamghevariya/repo-contextr
Project-URL: Repository, https://github.com/dharamghevariya/repo-contextr
Project-URL: Issues, https://github.com/dharamghevariya/repo-contextr/issues
Author-email: Dharam Ghevariya <dharamghevariya36@gmail.com>
License: MIT License
License-File: LICENSE
Keywords: ai,cli,context,git,llm,repository
Classifier: Development Status :: 4 - Beta
Classifier: Intended Audience :: Developers
Classifier: License :: OSI Approved :: MIT License
Classifier: Programming Language :: Python :: 3
Classifier: Programming Language :: Python :: 3.12
Classifier: Topic :: Software Development
Classifier: Topic :: Utilities
Requires-Python: >=3.12
Requires-Dist: rich>=13.0.0
Requires-Dist: typer>=0.9.0
